aka_stats/__init__.py
aka_stats/api.py
aka_stats/app.py
aka_stats/async_stats.py
aka_stats/prometheus.py
aka_stats/redis.py
aka_stats/settings.py
aka_stats/stats.py
aka_stats/testing.py
aka_stats-21.2.5.dist-info/entry_points.txt
aka_stats-21.2.5.dist-info/LICENSE
aka_stats-21.2.5.dist-info/WHEEL
aka_stats-21.2.5.dist-info/METADATA
aka_stats-21.2.5.dist-info/RECORD
