Metadata-Version: 2.1
Name: aka-stats
Version: 21.2.5
Summary: Module for keeping metrics about your application in Redis. The goal is to have an easy way to measure an application, and then expose these metrics through a HTTP API, either to process it in some web ui, or expose it to Prometheus.
Home-page: https://github.com/MichalMazurek/aka_stats
License: MIT
Author: Michal Mazurek
Author-email: mazurek.michal@gmail.com
Requires-Python: >=3.7,<4.0
Classifier: Development Status :: 5 - Production/Stable
Classifier: License :: OSI Approved :: MIT License
Classifier: Programming Language :: Python :: 3
Classifier: Programming Language :: Python :: 3.7
Classifier: Programming Language :: Python :: 3.8
Classifier: Topic :: Software Development :: Libraries :: Python Modules
Provides-Extra: fastapi
Requires-Dist: aioredis (>=1.3.1,<2.0.0)
Requires-Dist: fastapi (>=0.54.1,<0.55.0); extra == "fastapi"
Requires-Dist: pytz (>=2019.3,<2020.0)
Requires-Dist: redis (>=3.4.1,<4.0.0)
Project-URL: Repository, https://github.com/MichalMazurek/aka_stats
